domdiv/__init__.py
domdiv/cards.py
domdiv/config_options.py
domdiv/db.py
domdiv/draw.py
domdiv/main.py
domdiv/resource_handling.py
domdiv/card_db/cards_db.json.gz
domdiv/card_db/labels_db.json.gz
domdiv/card_db/sets_db.json.gz
domdiv/card_db/translation.md
domdiv/card_db/types_db.json.gz
domdiv/card_db/cs/bonuses_cs.json.gz
domdiv/card_db/cs/cards_cs.json.gz
domdiv/card_db/cs/sets_cs.json.gz
domdiv/card_db/cs/types_cs.json.gz
domdiv/card_db/de/bonuses_de.json.gz
domdiv/card_db/de/cards_de.json.gz
domdiv/card_db/de/sets_de.json.gz
domdiv/card_db/de/types_de.json.gz
domdiv/card_db/en_us/bonuses_en_us.json.gz
domdiv/card_db/en_us/cards_en_us.json.gz
domdiv/card_db/en_us/sets_en_us.json.gz
domdiv/card_db/en_us/types_en_us.json.gz
domdiv/card_db/es/bonuses_es.json.gz
domdiv/card_db/es/cards_es.json.gz
domdiv/card_db/es/sets_es.json.gz
domdiv/card_db/es/types_es.json.gz
domdiv/card_db/fr/bonuses_fr.json.gz
domdiv/card_db/fr/cards_fr.json.gz
domdiv/card_db/fr/sets_fr.json.gz
domdiv/card_db/fr/types_fr.json.gz
domdiv/card_db/it/bonuses_it.json.gz
domdiv/card_db/it/cards_it.json.gz
domdiv/card_db/it/sets_it.json.gz
domdiv/card_db/it/types_it.json.gz
domdiv/card_db/nl_nl/bonuses_nl_nl.json.gz
domdiv/card_db/nl_nl/cards_nl_nl.json.gz
domdiv/card_db/nl_nl/sets_nl_nl.json.gz
domdiv/card_db/nl_nl/types_nl_nl.json.gz
domdiv/card_db/xx/bonuses_xx.json.gz
domdiv/card_db/xx/cards_xx.json.gz
domdiv/card_db/xx/sets_xx.json.gz
domdiv/card_db/xx/translation.txt
domdiv/card_db/xx/types_xx.json.gz
domdiv/fonts/README.md
domdiv/images/action-shelter.png
domdiv/images/action-treasure.png
domdiv/images/action-victory.png
domdiv/images/action.png
domdiv/images/adventures_set.png
domdiv/images/alchemy_set.png
domdiv/images/allies_set.png
domdiv/images/ally.png
domdiv/images/animals.png
domdiv/images/artifact.png
domdiv/images/black_market_set.png
domdiv/images/boon.png
domdiv/images/card.png
domdiv/images/coin.png
domdiv/images/coin_small.png
domdiv/images/coin_small_0.png
domdiv-4.9.2.dist-info/licenses/LICENSE.md
domdiv-4.9.2.dist-info/METADATA
domdiv-4.9.2.dist-info/WHEEL
domdiv-4.9.2.dist-info/entry_points.txt
domdiv-4.9.2.dist-info/top_level.txt
domdiv-4.9.2.dist-info/RECORD
