Metadata-Version: 2.4
Name: domdiv
Version: 4.9.2
Summary: Divider Generation for the Dominion Card Game
Author-email: Peter Gorniak <sumpfork@mailmight.net>
Project-URL: Say Thanks, https://boardgamegeek.com/thread/926575/web-page-generate-tabbed-dividers
Project-URL: Source, https://github.com/sumpfork/dominiontabs
Project-URL: Issue Tracker, https://github.com/sumpfork/dominiontabs/issues
Project-URL: Homepage, http://domtabs.sandflea.org
Keywords: boardgame,cardgame,dividers
Requires-Python: >=3.8
License-File: LICENSE.md
Requires-Dist: reportlab
Requires-Dist: Pillow
Requires-Dist: configargparse
Requires-Dist: loguru
Provides-Extra: dev
Requires-Dist: build; extra == "dev"
Requires-Dist: twine; extra == "dev"
Requires-Dist: pre-commit; extra == "dev"
Requires-Dist: doit; extra == "dev"
Requires-Dist: pytest; extra == "dev"
Dynamic: license-file
